dcf_python_packaging_demo_upload/__init__.py
dcf_python_packaging_demo_upload/app.py
dcf_python_packaging_demo_upload-0.0.1.dist-info/LICENSE
dcf_python_packaging_demo_upload-0.0.1.dist-info/METADATA
dcf_python_packaging_demo_upload-0.0.1.dist-info/WHEEL
dcf_python_packaging_demo_upload-0.0.1.dist-info/entry_points.txt
dcf_python_packaging_demo_upload-0.0.1.dist-info/top_level.txt
dcf_python_packaging_demo_upload-0.0.1.dist-info/RECORD
